<root>
  <message info="Receiver: 7007. From: 127.0.0.1:62553" type="Received">
    <packet>I2J1bmRsZQAAAAAAAAAAAA==</packet>
  </message>
  <message info="Receiver: 7007. From: 127.0.0.1:62553" type="Received">
    <packet>I2J1bmRsZQAAAAAAAAAAAA==</packet>
  </message>
  <message info="Receiver: 7007. From: 127.0.0.1:62553" type="Received">
    <packet>I2J1bmRsZQAAAAAAAAAAAA==</packet>
  </message>
  <message info="Receiver: 7007. From: 127.0.0.1:62553" type="Received">
    <packet>I2J1bmRsZQAAAAAAAAAAAAAAABAvUGxheWVyACxpAAAAAAAB</packet>
  </message>
  <message info="Receiver: 7007. From: 127.0.0.1:62553" type="Received">
    <packet>I2J1bmRsZQAAAAAAAAAAAA==</packet>
  </message>
  <message info="Receiver: 7007. From: 127.0.0.1:62553" type="Received">
    <packet>I2J1bmRsZQAAAAAAAAAAAA==</packet>
  </message>
  <message info="Receiver: 7007. From: 127.0.0.1:62553" type="Received">
    <packet>I2J1bmRsZQAAAAAAAAAAAAAAABAvUGxheWVyACxpAAAAAAAB</packet>
  </message>
</root>